histexport/__init__.py
histexport/histexport.py
histexport-0.3.0.dist-info/LICENSE
histexport-0.3.0.dist-info/METADATA
histexport-0.3.0.dist-info/WHEEL
histexport-0.3.0.dist-info/entry_points.txt
histexport-0.3.0.dist-info/top_level.txt
histexport-0.3.0.dist-info/RECORD
