Metadata-Version: 2.1
Name: histexport
Version: 0.3.0
Summary: A Python utility to export Chromium-based browser history and downloads to various formats.
Home-page: https://github.com/darkarp/histexport
Author: Mario Nascimento
Author-email: mario@whitehathacking.tech
License: MIT
Keywords: history,browser,chromium,export,downloads,URLs
Platform: UNKNOWN
Classifier: Development Status :: 3 - Alpha
Classifier: Intended Audience :: Information Technology
Classifier: Intended Audience :: Developers
Classifier: Topic :: Security
Classifier: License :: OSI Approved :: MIT License
Classifier: Programming Language :: Python :: 3.7
Classifier: Programming Language :: Python :: 3.8
Classifier: Programming Language :: Python :: 3.9
Classifier: Programming Language :: Python :: 3.10
Classifier: Programming Language :: Python :: 3.11
Requires-Python: >=3.7
Requires-Dist: pandas>=1.0.0
Requires-Dist: openpyxl>=3.0.0
Requires-Dist: colorlog>=6.0.0
